aissemble_security/__init__.py
aissemble_security/pdp_client.py
aissemble_foundation_pdp_client_python-2.0.0.dist-info/LICENSE
aissemble_foundation_pdp_client_python-2.0.0.dist-info/METADATA
aissemble_foundation_pdp_client_python-2.0.0.dist-info/WHEEL
aissemble_foundation_pdp_client_python-2.0.0.dist-info/RECORD
